Metadata-Version: 2.1
Name: zocrypt
Version: 1.3.25
Summary: UNKNOWN
Home-page: https://github.com/SidmoGoesBrrr/zocrypt
Author: Siddhant Mohile
Author-email: meetsiddhant@gmail.com
License: MIT
Keywords: encrypt,decrypt,encoding,secret messages
Platform: UNKNOWN
